retail_data_sources/__init__.py
retail_data_sources/census/__init__.py
retail_data_sources/census/models/__init__.py
retail_data_sources/census/models/retail_sales.py
retail_data_sources/census/retail_sales_processor.py
retail_data_sources/fred/__init__.py
retail_data_sources/fred/classifier.py
retail_data_sources/fred/fetcher.py
retail_data_sources/fred/fred_api_handler.py
retail_data_sources/fred/fred_interpretation_rules.json
retail_data_sources/fred/models/__init__.py
retail_data_sources/fred/models/economic_metrics.py
retail_data_sources/fred/transformer.py
retail_data_sources/main.py
retail_data_sources/openweather/__init__.py
retail_data_sources/openweather/models/__init__.py
retail_data_sources/openweather/models/state_weather.py
retail_data_sources/openweather/weather_data_processor.py
retail_data_sources/snowflake/__init__.py
retail_data_sources/snowflake/census.py
retail_data_sources/snowflake/database_cursor.py
retail_data_sources/snowflake/fred.py
retail_data_sources/snowflake/openweather.py
retail_data_sources/utils/__init__.py
retail_data_sources/utils/constants.py
retail_data_sources/utils/logging.py
retail_data_sources-1.1.1.dist-info/LICENSE
retail_data_sources-1.1.1.dist-info/METADATA
retail_data_sources-1.1.1.dist-info/WHEEL
retail_data_sources-1.1.1.dist-info/RECORD
