Metadata-Version: 2.1
Name: retail-data-sources
Version: 1.1.1
Summary: Data Sources for Retail Demand Forecast
License: Apache-2.0
Author: Sai Ranga Reddy Nukala
Author-email: itsmerr17@gmail.com
Requires-Python: >=3.10,<4
Classifier: Development Status :: 4 - Beta
Classifier: License :: OSI Approved :: Apache Software License
Classifier: Programming Language :: Python :: 3
Classifier: Programming Language :: Python :: 3.10
Classifier: Programming Language :: Python :: 3.11
Classifier: Programming Language :: Python :: 3.12
Classifier: Programming Language :: Python :: 3.13
Requires-Dist: numpy (>=2.1.3,<3.0.0)
Requires-Dist: pandas (>=2.2.3,<3.0.0)
Requires-Dist: rapidfuzz (>=3.10.1,<4.0.0)
Requires-Dist: snowflake-connector-python (>=3.12.3,<4.0.0)
Requires-Dist: statsmodels (>=0.14.4,<0.15.0)
